<?xml version="1.0" encoding="utf-8"?>
<clothing-items>
 <clothing>
  <id>
   173812787
  </id>
  <name>
   Fila Sweater J-4136
  </name>
  <category>
   Sweater
  </category>
  <size>
   L
  </size>
  <color>
   Оранжевый
  </color>
  <material>
   Лен
  </material>
  <price>
   417400
  </price>
  <rating>
   3.4
  </rating>
  <reviews>
   966629
  </reviews>
  <new>
   +
  </new>
  <sporty>
   no
  </sporty>
 </clothing>
 <clothing>
  <id>
   985050202
  </id>
  <name>
   New Balance Handbags Q-7815
  </name>
  <category>
   Handbags
  </category>
  <size>
   XXL
  </size>
  <color>
   Оранжевый
  </color>
  <material>
   Лен
  </material>
  <price>
   797836
  </price>
  <rating>
   3.01
  </rating>
  <reviews>
   603220
  </reviews>
  <exclusive>
   no
  </exclusive>
  <sporty>
   yes
  </sporty>
 </clothing>
 <clothing>
  <id>
   661144386
  </id>
  <name>
   Under Armour Skirt I-5675
  </name>
  <category>
   Skirt
  </category>
  <size>
   S
  </size>
  <color>
   Желтый
  </color>
  <material>
   Хлопок
  </material>
  <price>
   392936
  </price>
  <rating>
   1.93
  </rating>
  <reviews>
   964068
  </reviews>
  <new>
   -
  </new>
  <sporty>
   no
  </sporty>
 </clothing>
 <clothing>
  <id>
   627734228
  </id>
  <name>
   Adidas Belts O-1998
  </name>
  <category>
   Belts
  </category>
  <size>
   S
  </size>
  <color>
   Зеленый
  </color>
  <material>
   Хлопок
  </material>
  <price>
   776782
  </price>
  <rating>
   1.58
  </rating>
  <reviews>
   347056
  </reviews>
  <exclusive>
   no
  </exclusive>
  <sporty>
   no
  </sporty>
 </clothing>
 <clothing>
  <id>
   949418951
  </id>
  <name>
   Under Armour Pants I-6904
  </name>
  <category>
   Pants
  </category>
  <size>
   M
  </size>
  <color>
   Голубой
  </color>
  <material>
   Вискоза
  </material>
  <price>
   282299
  </price>
  <rating>
   1.07
  </rating>
  <reviews>
   516024
  </reviews>
  <new>
   -
  </new>
  <exclusive>
   no
  </exclusive>
 </clothing>
 <clothing>
  <id>
   788059924
  </id>
  <name>
   Nike Umbrellas K-2056
  </name>
  <category>
   Umbrellas
  </category>
  <size>
   M
  </size>
  <color>
   Оранжевый
  </color>
  <material>
   Хлопок
  </material>
  <price>
   204478
  </price>
  <rating>
   1.82
  </rating>
  <reviews>
   890397
  </reviews>
  <new>
   +
  </new>
  <exclusive>
   no
  </exclusive>
  <sporty>
   no
  </sporty>
 </clothing>
 <clothing>
  <id>
   162569500
  </id>
  <name>
   Asics T-shirt O-3334
  </name>
  <category>
   T-shirt
  </category>
  <size>
   L
  </size>
  <color>
   Голубой
  </color>
  <material>
   Вискоза
  </material>
  <price>
   301655
  </price>
  <rating>
   1.61
  </rating>
  <reviews>
   689646
  </reviews>
  <sporty>
   yes
  </sporty>
 </clothing>
 <clothing>
  <id>
   882694533
  </id>
  <name>
   Converse Shirt S-8838
  </name>
  <category>
   Shirt
  </category>
  <size>
   M
  </size>
  <color>
   Голубой
  </color>
  <material>
   Лен
  </material>
  <price>
   755467
  </price>
  <rating>
   4.81
  </rating>
  <reviews>
   697452
  </reviews>
  <exclusive>
   no
  </exclusive>
 </clothing>
 <clothing>
  <id>
   617874967
  </id>
  <name>
   Under Armour Gloves I-2498
  </name>
  <category>
   Gloves
  </category>
  <size>
   S
  </size>
  <color>
   Фиолетовый
  </color>
  <material>
   Нейлон
  </material>
  <price>
   827468
  </price>
  <rating>
   3.82
  </rating>
  <reviews>
   339817
  </reviews>
  <sporty>
   no
  </sporty>
 </clothing>
 <clothing>
  <id>
   783896125
  </id>
  <name>
   New Balance Shoes D-8412
  </name>
  <category>
   Shoes
  </category>
  <size>
   M
  </size>
  <color>
   Красный
  </color>
  <material>
   Полиэстер
  </material>
  <price>
   202420
  </price>
  <rating>
   1.52
  </rating>
  <reviews>
   742962
  </reviews>
  <new>
   +
  </new>
  <sporty>
   no
  </sporty>
 </clothing>
 <clothing>
  <id>
   958948036
  </id>
  <name>
   Converse Shirt Z-6900
  </name>
  <category>
   Shirt
  </category>
  <size>
   M
  </size>
  <color>
   Фиолетовый
  </color>
  <material>
   Нейлон
  </material>
  <price>
   622002
  </price>
  <rating>
   2.89
  </rating>
  <reviews>
   705388
  </reviews>
  <sporty>
   no
  </sporty>
 </clothing>
 <clothing>
  <id>
   818133427
  </id>
  <name>
   Vans Pants Q-9093
  </name>
  <category>
   Pants
  </category>
  <size>
   S
  </size>
  <color>
   Красный
  </color>
  <material>
   Нейлон
  </material>
  <price>
   521618
  </price>
  <rating>
   1.64
  </rating>
  <reviews>
   726724
  </reviews>
  <exclusive>
   no
  </exclusive>
 </clothing>
 <clothing>
  <id>
   743654766
  </id>
  <name>
   Brooks Blouse O-6489
  </name>
  <category>
   Blouse
  </category>
  <size>
   M
  </size>
  <color>
   Голубой
  </color>
  <material>
   Хлопок
  </material>
  <price>
   308771
  </price>
  <rating>
   1.93
  </rating>
  <reviews>
   454558
  </reviews>
 </clothing>
 <clothing>
  <id>
   290491837
  </id>
  <name>
   Asics Sweater W-9694
  </name>
  <category>
   Sweater
  </category>
  <size>
   S
  </size>
  <color>
   Фиолетовый
  </color>
  <material>
   Лен
  </material>
  <price>
   544988
  </price>
  <rating>
   2.84
  </rating>
  <reviews>
   293926
  </reviews>
  <new>
   -
  </new>
  <sporty>
   no
  </sporty>
 </clothing>
 <clothing>
  <id>
   321403030
  </id>
  <name>
   Asics Handbags G-7401
  </name>
  <category>
   Handbags
  </category>
  <size>
   XXL
  </size>
  <color>
   Синий
  </color>
  <material>
   Шелк
  </material>
  <price>
   850557
  </price>
  <rating>
   2.42
  </rating>
  <reviews>
   221179
  </reviews>
  <exclusive>
   yes
  </exclusive>
  <sporty>
   yes
  </sporty>
 </clothing>
 <clothing>
  <id>
   473673557
  </id>
  <name>
   Brooks Jeans W-2746
  </name>
  <category>
   Jeans
  </category>
  <size>
   S
  </size>
  <color>
   Голубой
  </color>
  <material>
   Вискоза
  </material>
  <price>
   498813
  </price>
  <rating>
   4.17
  </rating>
  <reviews>
   473110
  </reviews>
  <new>
   +
  </new>
 </clothing>
 <clothing>
  <id>
   689695871
  </id>
  <name>
   Asics T-shirt F-4180
  </name>
  <category>
   T-shirt
  </category>
  <size>
   XXL
  </size>
  <color>
   Оранжевый
  </color>
  <material>
   Кожа
  </material>
  <price>
   122242
  </price>
  <rating>
   4.24
  </rating>
  <reviews>
   754540
  </reviews>
  <exclusive>
   no
  </exclusive>
  <sporty>
   no
  </sporty>
 </clothing>
 <clothing>
  <id>
   690744770
  </id>
  <name>
   DC Handbags D-5449
  </name>
  <category>
   Handbags
  </category>
  <size>
   XXL
  </size>
  <color>
   Зеленый
  </color>
  <material>
   Лен
  </material>
  <price>
   253300
  </price>
  <rating>
   2.3
  </rating>
  <reviews>
   661727
  </reviews>
  <new>
   -
  </new>
  <sporty>
   yes
  </sporty>
 </clothing>
 <clothing>
  <id>
   472229503
  </id>
  <name>
   Reebok T-shirt V-2115
  </name>
  <category>
   T-shirt
  </category>
  <size>
   L
  </size>
  <color>
   Оранжевый
  </color>
  <material>
   Вискоза
  </material>
  <price>
   641673
  </price>
  <rating>
   1.12
  </rating>
  <reviews>
   319576
  </reviews>
  <new>
   -
  </new>
  <exclusive>
   yes
  </exclusive>
 </clothing>
 <clothing>
  <id>
   700689806
  </id>
  <name>
   Ellesse Sweater M-8946
  </name>
  <category>
   Sweater
  </category>
  <size>
   XXL
  </size>
  <color>
   Синий
  </color>
  <material>
   Шерсть
  </material>
  <price>
   939013
  </price>
  <rating>
   4.9
  </rating>
  <reviews>
   158289
  </reviews>
  <exclusive>
   no
  </exclusive>
 </clothing>
 <clothing>
  <id>
   735451892
  </id>
  <name>
   Asics Shirt T-9273
  </name>
  <category>
   Shirt
  </category>
  <size>
   XXL
  </size>
  <color>
   Желтый
  </color>
  <material>
   Кожа
  </material>
  <price>
   188502
  </price>
  <rating>
   2.66
  </rating>
  <reviews>
   839060
  </reviews>
  <exclusive>
   yes
  </exclusive>
  <sporty>
   no
  </sporty>
 </clothing>
 <clothing>
  <id>
   779896671
  </id>
  <name>
   Under Armour Belts Z-6850
  </name>
  <category>
   Belts
  </category>
  <size>
   XL
  </size>
  <color>
   Голубой
  </color>
  <material>
   Вискоза
  </material>
  <price>
   578530
  </price>
  <rating>
   1.42
  </rating>
  <reviews>
   897978
  </reviews>
  <new>
   +
  </new>
  <exclusive>
   no
  </exclusive>
  <sporty>
   no
  </sporty>
 </clothing>
 <clothing>
  <id>
   407620705
  </id>
  <name>
   Under Armour Umbrellas O-7091
  </name>
  <category>
   Umbrellas
  </category>
  <size>
   XXL
  </size>
  <color>
   Красный
  </color>
  <material>
   Полиэстер
  </material>
  <price>
   382551
  </price>
  <rating>
   3.94
  </rating>
  <reviews>
   487824
  </reviews>
  <exclusive>
   no
  </exclusive>
 </clothing>
 <clothing>
  <id>
   994214496
  </id>
  <name>
   Asics Socks D-8512
  </name>
  <category>
   Socks
  </category>
  <size>
   M
  </size>
  <color>
   Красный
  </color>
  <material>
   Полиэстер
  </material>
  <price>
   872826
  </price>
  <rating>
   3.22
  </rating>
  <reviews>
   964647
  </reviews>
  <exclusive>
   no
  </exclusive>
  <sporty>
   no
  </sporty>
 </clothing>
 <clothing>
  <id>
   201200885
  </id>
  <name>
   Puma Sweater D-1158
  </name>
  <category>
   Sweater
  </category>
  <size>
   XL
  </size>
  <color>
   Красный
  </color>
  <material>
   Шерсть
  </material>
  <price>
   765811
  </price>
  <rating>
   3.65
  </rating>
  <reviews>
   929686
  </reviews>
  <sporty>
   no
  </sporty>
 </clothing>
 <clothing>
  <id>
   660131547
  </id>
  <name>
   Brooks Jacket W-5711
  </name>
  <category>
   Jacket
  </category>
  <size>
   XL
  </size>
  <color>
   Зеленый
  </color>
  <material>
   Нейлон
  </material>
  <price>
   646461
  </price>
  <rating>
   3.46
  </rating>
  <reviews>
   930177
  </reviews>
 </clothing>
 <clothing>
  <id>
   674966759
  </id>
  <name>
   DC Jeans J-4082
  </name>
  <category>
   Jeans
  </category>
  <size>
   S
  </size>
  <color>
   Голубой
  </color>
  <material>
   Кожа
  </material>
  <price>
   244582
  </price>
  <rating>
   1.82
  </rating>
  <reviews>
   592164
  </reviews>
  <new>
   -
  </new>
  <sporty>
   no
  </sporty>
 </clothing>
 <clothing>
  <id>
   791294247
  </id>
  <name>
   Asics Shoes R-4669
  </name>
  <category>
   Shoes
  </category>
  <size>
   XXL
  </size>
  <color>
   Желтый
  </color>
  <material>
   Шелк
  </material>
  <price>
   291474
  </price>
  <rating>
   3.85
  </rating>
  <reviews>
   180688
  </reviews>
  <new>
   +
  </new>
  <exclusive>
   no
  </exclusive>
  <sporty>
   no
  </sporty>
 </clothing>
 <clothing>
  <id>
   594856336
  </id>
  <name>
   New Balance Shirt A-9458
  </name>
  <category>
   Shirt
  </category>
  <size>
   XL
  </size>
  <color>
   Зеленый
  </color>
  <material>
   Вискоза
  </material>
  <price>
   969327
  </price>
  <rating>
   2.24
  </rating>
  <reviews>
   859369
  </reviews>
  <new>
   +
  </new>
 </clothing>
 <clothing>
  <id>
   336434197
  </id>
  <name>
   Brooks Jacket I-4890
  </name>
  <category>
   Jacket
  </category>
  <size>
   XL
  </size>
  <color>
   Желтый
  </color>
  <material>
   Полиэстер
  </material>
  <price>
   287245
  </price>
  <rating>
   1.37
  </rating>
  <reviews>
   192955
  </reviews>
  <new>
   -
  </new>
  <exclusive>
   no
  </exclusive>
 </clothing>
 <clothing>
  <id>
   798071993
  </id>
  <name>
   Brooks Blouse O-8045
  </name>
  <category>
   Blouse
  </category>
  <size>
   L
  </size>
  <color>
   Зеленый
  </color>
  <material>
   Лен
  </material>
  <price>
   307071
  </price>
  <rating>
   2.82
  </rating>
  <reviews>
   611301
  </reviews>
  <exclusive>
   yes
  </exclusive>
  <sporty>
   yes
  </sporty>
 </clothing>
 <clothing>
  <id>
   133639039
  </id>
  <name>
   Ellesse Hat U-2498
  </name>
  <category>
   Hat
  </category>
  <size>
   L
  </size>
  <color>
   Голубой
  </color>
  <material>
   Нейлон
  </material>
  <price>
   469620
  </price>
  <rating>
   4.71
  </rating>
  <reviews>
   73700
  </reviews>
  <sporty>
   yes
  </sporty>
 </clothing>
 <clothing>
  <id>
   278882007
  </id>
  <name>
   Puma T-shirt N-3238
  </name>
  <category>
   T-shirt
  </category>
  <size>
   L
  </size>
  <color>
   Оранжевый
  </color>
  <material>
   Лен
  </material>
  <price>
   710085
  </price>
  <rating>
   4.83
  </rating>
  <reviews>
   68399
  </reviews>
  <new>
   -
  </new>
  <sporty>
   yes
  </sporty>
 </clothing>
 <clothing>
  <id>
   397667588
  </id>
  <name>
   Ellesse Jacket S-1092
  </name>
  <category>
   Jacket
  </category>
  <size>
   L
  </size>
  <color>
   Красный
  </color>
  <material>
   Шелк
  </material>
  <price>
   663676
  </price>
  <rating>
   3.49
  </rating>
  <reviews>
   271896
  </reviews>
  <exclusive>
   no
  </exclusive>
 </clothing>
 <clothing>
  <id>
   117953405
  </id>
  <name>
   Reebok Shirt J-7422
  </name>
  <category>
   Shirt
  </category>
  <size>
   M
  </size>
  <color>
   Зеленый
  </color>
  <material>
   Шерсть
  </material>
  <price>
   800436
  </price>
  <rating>
   3.16
  </rating>
  <reviews>
   95270
  </reviews>
  <sporty>
   no
  </sporty>
 </clothing>
 <clothing>
  <id>
   649827943
  </id>
  <name>
   Lacoste Dress N-4283
  </name>
  <category>
   Dress
  </category>
  <size>
   XL
  </size>
  <color>
   Красный
  </color>
  <material>
   Шерсть
  </material>
  <price>
   219532
  </price>
  <rating>
   4.21
  </rating>
  <reviews>
   138247
  </reviews>
  <new>
   -
  </new>
 </clothing>
 <clothing>
  <id>
   771872120
  </id>
  <name>
   Lacoste Gloves Y-9914
  </name>
  <category>
   Gloves
  </category>
  <size>
   XXL
  </size>
  <color>
   Фиолетовый
  </color>
  <material>
   Шерсть
  </material>
  <price>
   229667
  </price>
  <rating>
   3.85
  </rating>
  <reviews>
   589461
  </reviews>
  <new>
   +
  </new>
  <exclusive>
   no
  </exclusive>
  <sporty>
   yes
  </sporty>
 </clothing>
 <clothing>
  <id>
   570802250
  </id>
  <name>
   Vans Shoes D-3277
  </name>
  <category>
   Shoes
  </category>
  <size>
   XL
  </size>
  <color>
   Оранжевый
  </color>
  <material>
   Лен
  </material>
  <price>
   242019
  </price>
  <rating>
   3.96
  </rating>
  <reviews>
   120073
  </reviews>
  <sporty>
   no
  </sporty>
 </clothing>
 <clothing>
  <id>
   666564554
  </id>
  <name>
   Brooks Gloves J-5158
  </name>
  <category>
   Gloves
  </category>
  <size>
   XXL
  </size>
  <color>
   Красный
  </color>
  <material>
   Вискоза
  </material>
  <price>
   384064
  </price>
  <rating>
   4.53
  </rating>
  <reviews>
   993614
  </reviews>
  <new>
   +
  </new>
  <exclusive>
   yes
  </exclusive>
  <sporty>
   no
  </sporty>
 </clothing>
 <clothing>
  <id>
   167843331
  </id>
  <name>
   Asics Jacket Z-1436
  </name>
  <category>
   Jacket
  </category>
  <size>
   M
  </size>
  <color>
   Оранжевый
  </color>
  <material>
   Кожа
  </material>
  <price>
   641541
  </price>
  <rating>
   4.41
  </rating>
  <reviews>
   746752
  </reviews>
  <new>
   -
  </new>
 </clothing>
 <clothing>
  <id>
   890458000
  </id>
  <name>
   Fila Hat J-5600
  </name>
  <category>
   Hat
  </category>
  <size>
   M
  </size>
  <color>
   Фиолетовый
  </color>
  <material>
   Хлопок
  </material>
  <price>
   609797
  </price>
  <rating>
   4.92
  </rating>
  <reviews>
   82547
  </reviews>
  <exclusive>
   no
  </exclusive>
 </clothing>
 <clothing>
  <id>
   563550041
  </id>
  <name>
   Ellesse Socks Y-8924
  </name>
  <category>
   Socks
  </category>
  <size>
   XXL
  </size>
  <color>
   Голубой
  </color>
  <material>
   Хлопок
  </material>
  <price>
   452512
  </price>
  <rating>
   4.97
  </rating>
  <reviews>
   19926
  </reviews>
  <new>
   -
  </new>
  <exclusive>
   no
  </exclusive>
  <sporty>
   no
  </sporty>
 </clothing>
 <clothing>
  <id>
   546391602
  </id>
  <name>
   Nike Sweater U-3857
  </name>
  <category>
   Sweater
  </category>
  <size>
   XXL
  </size>
  <color>
   Красный
  </color>
  <material>
   Шелк
  </material>
  <price>
   869584
  </price>
  <rating>
   2.53
  </rating>
  <reviews>
   974886
  </reviews>
  <new>
   -
  </new>
  <sporty>
   no
  </sporty>
 </clothing>
 <clothing>
  <id>
   774860558
  </id>
  <name>
   Adidas Jacket Z-5552
  </name>
  <category>
   Jacket
  </category>
  <size>
   XL
  </size>
  <color>
   Фиолетовый
  </color>
  <material>
   Шерсть
  </material>
  <price>
   571220
  </price>
  <rating>
   2.4
  </rating>
  <reviews>
   413431
  </reviews>
  <new>
   -
  </new>
  <sporty>
   yes
  </sporty>
 </clothing>
 <clothing>
  <id>
   641787258
  </id>
  <name>
   Converse Skirt A-5585
  </name>
  <category>
   Skirt
  </category>
  <size>
   S
  </size>
  <color>
   Голубой
  </color>
  <material>
   Кожа
  </material>
  <price>
   252936
  </price>
  <rating>
   3.98
  </rating>
  <reviews>
   303810
  </reviews>
  <new>
   +
  </new>
 </clothing>
 <clothing>
  <id>
   481865820
  </id>
  <name>
   Brooks Shoes L-7724
  </name>
  <category>
   Shoes
  </category>
  <size>
   S
  </size>
  <color>
   Фиолетовый
  </color>
  <material>
   Нейлон
  </material>
  <price>
   721502
  </price>
  <rating>
   1.17
  </rating>
  <reviews>
   720825
  </reviews>
  <new>
   +
  </new>
  <exclusive>
   yes
  </exclusive>
 </clothing>
 <clothing>
  <id>
   802020815
  </id>
  <name>
   Asics Socks S-9774
  </name>
  <category>
   Socks
  </category>
  <size>
   XXL
  </size>
  <color>
   Красный
  </color>
  <material>
   Шерсть
  </material>
  <price>
   645823
  </price>
  <rating>
   3.18
  </rating>
  <reviews>
   119837
  </reviews>
  <sporty>
   no
  </sporty>
 </clothing>
 <clothing>
  <id>
   195599214
  </id>
  <name>
   New Balance Gloves K-2967
  </name>
  <category>
   Gloves
  </category>
  <size>
   S
  </size>
  <color>
   Зеленый
  </color>
  <material>
   Вискоза
  </material>
  <price>
   632233
  </price>
  <rating>
   4.52
  </rating>
  <reviews>
   154948
  </reviews>
  <new>
   -
  </new>
  <exclusive>
   no
  </exclusive>
  <sporty>
   no
  </sporty>
 </clothing>
 <clothing>
  <id>
   391915176
  </id>
  <name>
   Fila Blouse T-1073
  </name>
  <category>
   Blouse
  </category>
  <size>
   XL
  </size>
  <color>
   Фиолетовый
  </color>
  <material>
   Нейлон
  </material>
  <price>
   758446
  </price>
  <rating>
   1.08
  </rating>
  <reviews>
   462350
  </reviews>
  <exclusive>
   yes
  </exclusive>
  <sporty>
   no
  </sporty>
 </clothing>
</clothing-items>
